shopeadion/__init__.py
shopeadion/cachesupport.py
shopeadion/dynamic_cache.py
shopeadion/hooks.py
shopeadion/loggingsupport.py
shopeadion/utils.py
shopeadion-0.0.5.dist-info/METADATA
shopeadion-0.0.5.dist-info/WHEEL
shopeadion-0.0.5.dist-info/top_level.txt
shopeadion-0.0.5.dist-info/RECORD
