Metadata-Version: 2.1
Name: shopeadion
Version: 0.0.5
Summary: This is a tool created for caching
